{
	"info": {
		"_postman_id": "cd28042c-a8e2-4c62-82ea-15e95de21a01",
		"name": "3_Creditaccount",
		"schema": "https://schema.getpostman.com/json/collection/v2.1.0/collection.json",
		"_exporter_id": "27524141"
	},
	"item": [
		{
			"name": "insertCreditaccount",
			"request": {
				"method": "POST",
				"header": [],
				"body": {
					"mode": "raw",
					"raw": "{\r\n  \"customer\": {\r\n    \"id\": 4\r\n  },\r\n  \"admin\": {\r\n    \"id\": 3\r\n  },\r\n  \"active\": true,\r\n  \"maxCredit\": 300,\r\n  \"currentCredit\": 0,\r\n  \"creditTypeOfRate\": \"TEA\",\r\n  \"creditRate\": 0.05,\r\n  \"creditCompounding\": 0,\r\n  \"invoicePenaltyRateType\": \"TEA\",\r\n  \"invoicePenaltyRate\": 0.02,\r\n  \"invoicePenaltyCompouding\": 0,\r\n  \"installmentPenaltyRateType\": \"TEA\",\r\n  \"installmentPenaltyRate\": 0.03,\r\n  \"installmentPenaltyCompouding\": 0,\r\n  \"invoiceCompensatoryRateType\": \"TEA\",\r\n  \"invoiceCompensatoryRate\": 0.01,\r\n  \"invoiceCompensatoryCompouding\": 0,\r\n  \"installmentCompensatoryRateType\": \"TEA\",\r\n  \"installmentCompensatoryRate\": 0.015,\r\n  \"installmentCompensatoryCompouding\": 0\r\n}\r\n",
					"options": {
						"raw": {
							"language": "json"
						}
					}
				},
				"url": {
					"raw": "http://localhost:8080/creditaccount",
					"protocol": "http",
					"host": [
						"localhost"
					],
					"port": "8080",
					"path": [
						"creditaccount"
					]
				}
			},
			"response": []
		},
		{
			"name": "getCreditaccounts",
			"request": {
				"method": "GET",
				"header": [],
				"url": {
					"raw": "http://localhost:8080/creditaccount",
					"protocol": "http",
					"host": [
						"localhost"
					],
					"port": "8080",
					"path": [
						"creditaccount"
					]
				}
			},
			"response": []
		},
		{
			"name": "updateCreditaccount",
			"request": {
				"method": "PUT",
				"header": [],
				"body": {
					"mode": "raw",
					"raw": "{\r\n  \"customer\": {\r\n    \"id\": 4\r\n  },\r\n  \"admin\": {\r\n    \"id\": 3\r\n  },\r\n  \"active\": false,\r\n  \"maxCredit\": 500,\r\n  \"currentCredit\": 500,\r\n  \"creditTypeOfRate\": \"TEA\",\r\n  \"creditRate\": 0.05,\r\n  \"creditCompounding\": 0,\r\n  \"invoicePenaltyRateType\": \"TEA\",\r\n  \"invoicePenaltyRate\": 0.02,\r\n  \"invoicePenaltyCompouding\": 0,\r\n  \"installmentPenaltyRateType\": \"TEA\",\r\n  \"installmentPenaltyRate\": 0.03,\r\n  \"installmentPenaltyCompouding\": 0,\r\n  \"invoiceCompensatoryRateType\": \"TEA\",\r\n  \"invoiceCompensatoryRate\": 0.01,\r\n  \"invoiceCompensatoryCompouding\": 0,\r\n  \"installmentCompensatoryRateType\": \"TEA\",\r\n  \"installmentCompensatoryRate\": 0.015,\r\n  \"installmentCompensatoryCompouding\": 0\r\n}\r\n",
					"options": {
						"raw": {
							"language": "json"
						}
					}
				},
				"url": {
					"raw": "http://localhost:8080/creditaccount/5",
					"protocol": "http",
					"host": [
						"localhost"
					],
					"port": "8080",
					"path": [
						"creditaccount",
						"5"
					]
				}
			},
			"response": []
		},
		{
			"name": "deleteCreditaccount",
			"request": {
				"method": "DELETE",
				"header": [],
				"url": {
					"raw": "http://localhost:8080/creditaccount/4",
					"protocol": "http",
					"host": [
						"localhost"
					],
					"port": "8080",
					"path": [
						"creditaccount",
						"4"
					]
				}
			},
			"response": []
		},
		{
			"name": "getCreditaccountById",
			"request": {
				"method": "GET",
				"header": [],
				"url": {
					"raw": "http://localhost:8080/creditaccount/5",
					"protocol": "http",
					"host": [
						"localhost"
					],
					"port": "8080",
					"path": [
						"creditaccount",
						"5"
					]
				}
			},
			"response": []
		}
	]
}